src/__init__.py
src/dwlfy.py
DWLFY-1.0.1.dist-info/LICENSE
DWLFY-1.0.1.dist-info/METADATA
DWLFY-1.0.1.dist-info/WHEEL
DWLFY-1.0.1.dist-info/top_level.txt
DWLFY-1.0.1.dist-info/RECORD
