Metadata-Version: 2.1
Name: DWLFY
Version: 1.0.1
Summary: The dwlfy library is a powerful and user-friendly tool designed to download videos from YouTube with options for video quality and format, along with an integrated MP3 conversion feature. This library is ideal for users who want flexibility in downloading, organizing, and converting YouTube content for offline use.
Home-page: https://github.com/JkaiPrime/dwlfy
Author: Lucas Guimaraes Moreira
Author-email: lucasgmoreira002@gmail.com
License: MIT
Classifier: Programming Language :: Python :: 3
Classifier: License :: OSI Approved :: MIT License
Classifier: Operating System :: OS Independent
Requires-Python: >=3.6
License-File: LICENSE
Requires-Dist: ffmpeg
Requires-Dist: yt-dlp
